[
  // {
  //   // TODO
  //   "key": "ctrl+alt+n",
  //   "command": "type",
  //   "args": {
  //     "text": "♮"
  //   }
  // },
  // {
  //   "key": "ctrl+alt+b",
  //   "command": "type",
  //   "args": {
  //     "text": "♭"
  //   }
  // },
  // {
  //   "key": "ctrl+alt+shift+b",
  //   "command": "type",
  //   "args": {
  //     "text": "𝄫"
  //   }
  // },
  // {
  //   "key": "ctrl+alt+3",
  //   "command": "type",
  //   "args": {
  //     "text": "♯"
  //   }
  // },
  // {
  //   "key": "ctrl+alt+shift+3",
  //   "command": "type",
  //   "args": {
  //     "text": "𝄪"
  //   }
  // },
  {
    // Z
    "key": "ctrl+shift+alt+` ctrl+shift+alt+z",
    "command": "undo"
  },
  {
    // C
    "key": "ctrl+shift+alt+` ctrl+shift+alt+/",
    "command": "editor.action.commentLine"
  },
  {
    // S
    "key": "ctrl+shift+alt+` ctrl+shift+alt+s",
    "command": "workbench.action.files.save"
  },
  {
    // Copy paste keys
    "key": "ctrl+shift+alt+` ctrl+shift+alt+c",
    "command": "editor.action.clipboardCopyAction"
  },
  {
    // Copy paste keys
    "key": "ctrl+shift+alt+` ctrl+alt+c",
    "command": "editor.action.clipboardCutAction"
  },
  {
    "key": "ctrl+shift+alt+` ctrl+shift+alt+v",
    "command": "editor.action.clipboardPasteAction"
  },
  {
    // top right
    "key": "ctrl+shift+alt+` ctrl+shift+alt+3",
    "command": "explorer.newFile"
  },
  {
    "key": "ctrl+shift+alt+` ctrl+shift+alt+r",
    "command": "explorer.newFolder"
  },
  {
    // View switches
    "key": "ctrl+shift+alt+` ctrl+shift+alt+left",
    "command": "workbench.action.previousEditor"
  },
  {
    "key": "ctrl+shift+alt+` ctrl+shift+alt+right",
    "command": "workbench.action.nextEditor"
  },
  {
    "key": "ctrl+shift+alt+` ctrl+shift+alt+down",
    "command": "workbench.action.closeActiveEditor"
  },
  {
    "key": "ctrl+shift+alt+` ctrl+shift+alt+up",
    "command": "workbench.action.quickOpen"
  },
  {
    // group switches
    "key": "ctrl+shift+alt+` ctrl+shift+alt+j",
    "command": "workbench.action.focusLeftGroup"
  },
  {
    "key": "ctrl+shift+alt+` ctrl+shift+alt+k",
    "command": "workbench.action.focusAboveGroup"
  },
  {
    "key": "ctrl+shift+alt+` ctrl+shift+alt+l",
    "command": "workbench.action.focusBelowGroup"
  },
  {
    "key": "ctrl+shift+alt+` ctrl+shift+alt+;",
    "command": "workbench.action.focusRightGroup"
  },
  {
    // create group switches
    "key": "ctrl+shift+alt+` ctrl+shift+alt+u",
    "command": "workbench.action.newGroupLeft"
  },
  {
    "key": "ctrl+shift+alt+` ctrl+shift+alt+i",
    "command": "workbench.action.newGroupAbove"
  },
  {
    "key": "ctrl+shift+alt+` ctrl+shift+alt+o",
    "command": "workbench.action.newGroupBelow"
  },
  {
    "key": "ctrl+shift+alt+` ctrl+shift+alt+p",
    "command": "workbench.action.newGroupRight"
  },
  {
    "key": "ctrl+shift+alt+` ctrl+alt+shift+\\",
    "command": "workbench.action.closeGroup"
  },
  {
    // numpad layer keys
    "key": "ctrl+shift+alt+` ctrl+alt+n",
    "command": "editor.action.addSelectionToPreviousFindMatch"
  },
  {
    "key": "ctrl+shift+alt+` ctrl+shift+alt+n",
    "command": "editor.action.addSelectionToNextFindMatch"
  },
  {
    // R
    "key": "ctrl+shift+alt+` ctrl+shift+alt+r",
    "command": "renameFile"
  },
  {
    // Wheel click
    "key": "ctrl+shift+alt+` ctrl+shift+alt+`",
    "command": "workbench.action.showCommands"
  },
  {
    // H
    "key": "ctrl+shift+alt+` ctrl+shift+alt+h",
    "command": "workbench.action.replaceInFiles"
  },
  // T
  {
    "key": "ctrl+shift+alt+` ctrl+shift+alt+t",
    "command": "workbench.action.terminal.toggleTerminal"
  },
  {
    // F
    "key": "ctrl+shift+alt+` ctrl+shift+alt+f",
    "command": "workbench.view.explorer"
  },
  // B
  {
    "key": "ctrl+shift+alt+` ctrl+shift+alt+b",
    "command": "workbench.action.toggleSidebarVisibility"
  },
  {
    "key": "ctrl+shift+alt+` ctrl+shift+alt+]",
    "command": "workbench.action.closeAllEditors"
  },
  {
    "key": "ctrl+shift+alt+` ctrl+shift+alt+q",
    "command": "actions.find"
  },
  {
    "key": "ctrl+shift+alt+` ctrl+shift+alt+a",
    "command": "editor.action.changeAll"
  },
  {
    "key": "ctrl+shift+alt+` ctrl+shift+alt+y",
    "command": "editor.action.rename"
  },
  {
    "key": "ctrl+shift+alt+` ctrl+alt+tab",
    "command": "workbench.action.moveSidePanelToPanel"
  },
  {
    "key": "ctrl+shift+alt+` ctrl+shift+alt+tab",
    "command": "workbench.action.movePanelToSidePanel"
  },
  {
    "key": "ctrl+shift+alt+` ctrl+shift+alt+6",
    "command": "github.copilot.toggleCopilot"
  },
  {
    "key": "ctrl+shift+alt+` ctrl+shift+alt+7",
    "command": "github.copilot.generate"
  },
  {
    "key": "ctrl+shift+alt+` ctrl+shift+alt+8",
    "command": "editor.action.inlineSuggest.commit"
  },
  {
    "key": "ctrl+shift+alt+` ctrl+shift+alt+9",
    "command": "editor.action.inlineSuggest.showNext"
  },
  {
    "key": "ctrl+shift+alt+` ctrl+shift+alt+0",
    "command": "editor.action.inlineSuggest.showPrevious"
  },
  {
    "key": "ctrl+shift+alt+` ctrl+shift+alt+-",
    "command": "editor.action.inlineSuggest.hide"
  },
  {
    "key": "ctrl+shift+alt+` ctrl+shift+alt+=",
    "command": "editor.action.inlineSuggest.trigger"
  }
  // {
  //   "key": "ctrl+shift+alt+` ctrl+shift+alt+z",
  //   "command":
  // },
  // {
  //   "key": "ctrl+shift+alt+` ctrl+shift+alt+z",
  //   "command":
  // },
  // {
  //   "key": "ctrl+shift+alt+` ctrl+shift+alt+z",
  //   "command":
  // },
  // {
  //   "key": "ctrl+shift+alt+` ctrl+shift+alt+z",
  //   "command":
  // },
]
